pybl3p/__init__.py
pybl3p/private.py
pybl3p/public.py
pybl3p/py.typed
pybl3p/requests.py
pybl3p-0.4.dist-info/LICENSE
pybl3p-0.4.dist-info/WHEEL
pybl3p-0.4.dist-info/METADATA
pybl3p-0.4.dist-info/RECORD
