Metadata-Version: 2.1
Name: pybl3p
Version: 0.4
Summary: A python wrapper for the bl3p cryptocurrency exchange
Home-page: https://github.com/gijzelaerr/pybl3p
License: MIT
Author: Gijs Molenaar
Author-email: gijs@pythonic.nl
Requires-Python: >=3.6,<4.0
Classifier: License :: OSI Approved :: MIT License
Classifier: Programming Language :: Python :: 3
Classifier: Programming Language :: Python :: 3.6
Classifier: Programming Language :: Python :: 3.7
Classifier: Programming Language :: Python :: 3.8
Requires-Dist: notebook
Requires-Dist: pandas
Requires-Dist: requests
Requires-Dist: websockets
Project-URL: Repository, https://github.com/gijzelaerr/pybl3p
